sphereob/__init__.py
sphereob/resources.py
sphereob/sphere_main.py
sphereob/sphere_response.py
sphereoverburden2-0.1.0.dist-info/METADATA
sphereoverburden2-0.1.0.dist-info/WHEEL
sphereoverburden2-0.1.0.dist-info/entry_points.txt
sphereoverburden2-0.1.0.dist-info/top_level.txt
sphereoverburden2-0.1.0.dist-info/RECORD
