Metadata-Version: 2.1
Name: sphereoverburden2
Version: 0.1.0
Summary: A utility to calculate and plot sphere-overburden EM response
Home-page: http://github.com/yourusername/sphereresponse
Author: Your Name
Author-email: your.email@example.com
Classifier: Programming Language :: Python :: 3
Classifier: License :: OSI Approved :: MIT License
Classifier: Operating System :: OS Independent
Requires-Python: >=3.6
Requires-Dist: PyQt5
Requires-Dist: numpy
Requires-Dist: matplotlib
Requires-Dist: pandas
Requires-Dist: scipy
